get_free_proxy/__init__.py
get_free_proxy/db/File.py
get_free_proxy/db/MySql.py
get_free_proxy/db/Redis.py
get_free_proxy/db/__init__.py
get_free_proxy/db/base.py
get_free_proxy/generator/GenProxy.py
get_free_proxy/generator/GenProxyFromPage.py
get_free_proxy/generator/__init__.py
get_free_proxy/helper/Checker.py
get_free_proxy/helper/PreFilter.py
get_free_proxy/helper/__init__.py
get_free_proxy/main/__init__.py
get_free_proxy/main/main.py
get_free_proxy/self/EnumMatchInst.py
get_free_proxy/self/SelfEnum.py
get_free_proxy/self/SelfException.py
get_free_proxy/self/__init__.py
get_free_proxy/setting/Setting.py
get_free_proxy/setting/__init__.py
get_free_proxy-0.1.2.dist-info/LICENSE
get_free_proxy-0.1.2.dist-info/METADATA
get_free_proxy-0.1.2.dist-info/WHEEL
get_free_proxy-0.1.2.dist-info/top_level.txt
get_free_proxy-0.1.2.dist-info/RECORD
