Metadata-Version: 2.1
Name: get-free-proxy
Version: 0.1.2
Summary: A package to get free proxy
Home-page: https://github.com/zwzw911/get-free-proxy
Author: zwzw911
Author-email: zwzw911110@163.com
License: UNKNOWN
Platform: UNKNOWN
Classifier: Programming Language :: Python :: 3
Classifier: License :: OSI Approved :: MIT License
Classifier: Operating System :: Microsoft :: Windows
Requires-Python: >=3.6
